fmover/__init__.py
fmover/base_logger.py
fmover/cli.py
fmover/config.py
fmover/configs.py
fmover/file_property.py
fmover/interpreter.py
fmover/mover.py
fmover-0.1.0.dist-info/WHEEL
fmover-0.1.0.dist-info/entry_points.txt
fmover-0.1.0.dist-info/LICENSE.txt
fmover-0.1.0.dist-info/METADATA
fmover-0.1.0.dist-info/RECORD
